{
  "id": "vI3EMpIgN5sPPTE",
  "unique_key": "https://www.facebook.com/maohievan/posts/1978863362556695?ref=embed_post",
  "order_no": null,
  "handled_at": "2025-05-17 11:49:57.729107+00:00",
  "request": {
    "url": "https://www.facebook.com/maohievan/posts/1978863362556695?ref=embed_post",
    "method": "GET",
    "headers": {},
    "payload": null,
    "user_data": {
      "__crawlee": {
        "state": 3
      }
    },
    "retry_count": 0,
    "no_retry": false,
    "loaded_url": "https://www.facebook.com/maohievan/posts/1978863362556695?ref=embed_post",
    "handled_at": "2025-05-17 11:49:57.729107+00:00",
    "unique_key": "https://www.facebook.com/maohievan/posts/1978863362556695?ref=embed_post",
    "id": "vI3EMpIgN5sPPTE"
  }
}